validclust/__init__.py
validclust/indices.py
validclust/validclust.py
validclust-0.1.1.dist-info/LICENSE.txt
validclust-0.1.1.dist-info/METADATA
validclust-0.1.1.dist-info/WHEEL
validclust-0.1.1.dist-info/top_level.txt
validclust-0.1.1.dist-info/RECORD
