Metadata-Version: 2.1
Name: validclust
Version: 0.1.1
Summary: Validate clustering results
Home-page: https://validclust.readthedocs.io
Author: Christopher Baker
Author-email: chriscrewbaker@gmail.com
License: LICENSE.txt
Platform: UNKNOWN
Requires-Python: >=3.5
Requires-Dist: scikit-learn
Requires-Dist: pandas
Requires-Dist: numpy (>=1.16.5)
Requires-Dist: seaborn
Requires-Dist: matplotlib
Requires-Dist: packaging
